clld_phylogeny_plugin/__init__.py
clld_phylogeny_plugin/datatables.py
clld_phylogeny_plugin/interfaces.py
clld_phylogeny_plugin/models.py
clld_phylogeny_plugin/tree.py
clld_phylogeny_plugin/static/clld_phylogeny_plugin.js
clld_phylogeny_plugin/static/d3.v5.js
clld_phylogeny_plugin/static/phylotree.css
clld_phylogeny_plugin/static/phylotree.js
clld_phylogeny_plugin/static/underscore-min.js
clld_phylogeny_plugin/templates/tree.mako
clld_phylogeny_plugin/templates/parameter/valuetable_html.mako
clld_phylogeny_plugin/templates/phylogeny/description_html.mako
clld_phylogeny_plugin/templates/phylogeny/detail_html.mako
clld_phylogeny_plugin/templates/phylogeny/index_html.mako
clld_phylogeny_plugin-1.6.0.dist-info/LICENSE
clld_phylogeny_plugin-1.6.0.dist-info/METADATA
clld_phylogeny_plugin-1.6.0.dist-info/WHEEL
clld_phylogeny_plugin-1.6.0.dist-info/top_level.txt
clld_phylogeny_plugin-1.6.0.dist-info/RECORD
