Metadata-Version: 2.1
Name: clld-phylogeny-plugin
Version: 1.6.0
Summary: A clld plugin to support language phylogenies
Home-page: https://github.com/clld-phylogeny-plugin
Author: Robert Forkel and Hans-Jörg Bibiko
Author-email: dlce.rdm@eva.mpg.de
License: Apache 2.0
Keywords: linguistics
Platform: any
Classifier: Development Status :: 5 - Production/Stable
Classifier: Intended Audience :: Developers
Classifier: Intended Audience :: Science/Research
Classifier: Natural Language :: English
Classifier: Operating System :: OS Independent
Classifier: Programming Language :: Python :: 3
Classifier: Programming Language :: Python :: 3.8
Classifier: Programming Language :: Python :: 3.9
Classifier: Programming Language :: Python :: 3.10
Classifier: Programming Language :: Python :: 3.11
Classifier: Programming Language :: Python :: 3.12
Classifier: Programming Language :: Python :: Implementation :: CPython
Classifier: Programming Language :: Python :: Implementation :: PyPy
Classifier: License :: OSI Approved :: Apache Software License
Requires-Python: >=3.8
License-File: LICENSE
Requires-Dist: newick
Requires-Dist: attrs (>=18.1)
Requires-Dist: clld (>=4.0.3)
Requires-Dist: sqlalchemy
Requires-Dist: zope.interface
Provides-Extra: dev
Requires-Dist: tox ; extra == 'dev'
Requires-Dist: flake8 ; extra == 'dev'
Requires-Dist: wheel (>=0.36) ; extra == 'dev'
Requires-Dist: twine ; extra == 'dev'
Provides-Extra: test
Requires-Dist: pytest-clld ; extra == 'test'
Requires-Dist: pytest (>=5) ; extra == 'test'
Requires-Dist: pytest-mock ; extra == 'test'
Requires-Dist: pytest-cov ; extra == 'test'
Requires-Dist: coverage (>=4.2) ; extra == 'test'
Requires-Dist: webtest ; extra == 'test'
